LICENSE.txt
MANIFEST.in
README.md
setup.cfg
setup.py
yanagiba/__init__.py
yanagiba/cmd_line.py
yanagiba.egg-info/PKG-INFO
yanagiba.egg-info/SOURCES.txt
yanagiba.egg-info/dependency_links.txt
yanagiba.egg-info/entry_points.txt
yanagiba.egg-info/not-zip-safe
yanagiba.egg-info/requires.txt
yanagiba.egg-info/top_level.txt