Metadata-Version: 1.1
Name: yanagiba
Version: 1.0.0
Summary: Filter short or low quality Oxford Nanopore reads which have been basecalled with Albacore.
Home-page: https://github.com/Adamtaranto/Yanagiba
Author: Adam Taranto
Author-email: adam.taranto@anu.edu.au
License: MIT
Keywords: Albacore,Nanopore,basecalling,genome,DNA,sequencing
Platform: UNKNOWN
Classifier: Programming Language :: Python :: 2.7
Classifier: Programming Language :: Python :: 3
Classifier: Development Status :: 4 - Beta
Classifier: Environment :: Console
Classifier: Operating System :: OS Independent
Classifier: Intended Audience :: Science/Research
Classifier: Natural Language :: English
Classifier: Topic :: Scientific/Engineering :: Bio-Informatics
Classifier: Topic :: Software Development :: Libraries :: Python Modules
Classifier: License :: OSI Approved :: MIT License
